__init__.py
NeurosphereClassifier/__init__.py
NeurosphereClassifier/dataset.py
NeurosphereClassifier/model.py
NeurosphereClassifier/plot.py
NeurosphereClassifier/utils.py
neurospherespikeclassifiercnn-0.0.1.dist-info/licenses/LICENSE
neurospherespikeclassifiercnn-0.0.1.dist-info/METADATA
neurospherespikeclassifiercnn-0.0.1.dist-info/WHEEL
neurospherespikeclassifiercnn-0.0.1.dist-info/top_level.txt
neurospherespikeclassifiercnn-0.0.1.dist-info/RECORD
