Metadata-Version: 2.4
Name: NeurosphereSpikeClassifierCNN
Version: 0.0.1
Summary: CNN Model for neural spike classification
Author-email: "Ylan A. CLODINE-FLORENT" <clodine-florent.ylan@outlook.com>
Maintainer-email: Tissue Engineering Group - HEPIA <adrien.roux@hesge.ch>
License-Expression: GPL-3.0-or-later
Project-URL: Homepage, https://github.com/RARE-DOLL-MIHAIL/Neurosphere-Spike-Classifier
Project-URL: Issues, https://github.com/RARE-DOLL-MIHAIL/Neurosphere-Spike-Classifier/issues
Classifier: Intended Audience :: Science/Research
Classifier: Topic :: Scientific/Engineering :: Artificial Intelligence
Classifier: Topic :: Scientific/Engineering :: Human Machine Interfaces
Classifier: Topic :: Scientific/Engineering :: Information Analysis
Classifier: Programming Language :: Python :: 3.10
Classifier: Operating System :: Microsoft :: Windows :: Windows 11
Requires-Python: >=3.10.13
License-File: LICENSE
Requires-Dist: keras==2.10.0
Requires-Dist: matplotlib==3.10.1
Requires-Dist: numpy==1.26.4
Requires-Dist: pandas==2.2.3
Requires-Dist: scikit-learn==1.6.1
Requires-Dist: tensorflow==2.10.0
Dynamic: license-file
